{
    "quotes": [
      {
        "text": "Be yourself; everyone else is already taken.",
        "author": "Oscar Wilde"
      },
      {
        "text": "Two things are infinite: the universe and human stupidity; and I'm not sure about the universe.",
        "author": "Albert Einstein"
      },
      {
        "text": "The only way to do great work is to love what you do.",
        "author": "Steve Jobs"
      },
      {
        "text": "Life is what happens when you're busy making other plans.",
        "author": "John Lennon"
      },
      {
        "text": "The future belongs to those who believe in the beauty of their dreams.",
        "author": "Eleanor Roosevelt"
      },
      {
        "text": "In three words I can sum up everything I've learned about life: it goes on.",
        "author": "Robert Frost"
      },
      {
        "text": "The best time to plant a tree was 20 years ago. The second best time is now.",
        "author": "Chinese Proverb"
      },
      {
        "text": "Happiness is not something ready-made. It comes from your own actions.",
        "author": "Dalai Lama"
      },
      {
        "text": "Your time is limited, don't waste it living someone else's life.",
        "author": "Steve Jobs"
      },
      {
        "text": "The journey of a thousand miles begins with one step.",
        "author": "Lao Tzu"
      }
    ]
  }